aiida_sshonly/__init__.py
aiida_sshonly/transports/__init__.py
aiida_sshonly/transports/ssh.py
aiida_sshonly/transports/sshonly.py
aiida_sshonly-0.1.0a3.dist-info/LICENSE
aiida_sshonly-0.1.0a3.dist-info/METADATA
aiida_sshonly-0.1.0a3.dist-info/WHEEL
aiida_sshonly-0.1.0a3.dist-info/entry_points.txt
aiida_sshonly-0.1.0a3.dist-info/top_level.txt
aiida_sshonly-0.1.0a3.dist-info/RECORD
